dmAsync/__init__.py
dmAsync/connection.py
dmAsync/log.py
dmAsync/pool.py
dmAsync/utils.py
dmasync-1.0.0.dist-info/licenses/LICENSE
dmasync-1.0.0.dist-info/METADATA
dmasync-1.0.0.dist-info/WHEEL
dmasync-1.0.0.dist-info/top_level.txt
dmasync-1.0.0.dist-info/RECORD
