Metadata-Version: 2.4
Name: dmAsync
Version: 1.0.0
Summary: Asynchronous compatibility package for DM
Author: Dameng
Author-email: 
Keywords: DM async
License-File: LICENSE
Requires-Dist: dmPython
Dynamic: author
Dynamic: keywords
Dynamic: license-file
Dynamic: requires-dist
Dynamic: summary
